ansys/turbogrid/core/__init__.py
ansys/turbogrid/core/inf_parser/__init__.py
ansys/turbogrid/core/inf_parser/inf_parser.py
ansys/turbogrid/core/launcher/container_helpers.py
ansys/turbogrid/core/launcher/deploy_tg_container.py
ansys/turbogrid/core/launcher/launcher.py
ansys/turbogrid/core/mesh_statistics/__init__.py
ansys/turbogrid/core/mesh_statistics/mesh_statistics.py
ansys/turbogrid/core/multi_blade_row/__init__.py
ansys/turbogrid/core/multi_blade_row/multi_blade_row.py
ansys/turbogrid/core/multi_blade_row/multi_blade_row_batch.py
ansys/turbogrid/core/multi_blade_row/report_template.html
ansys/turbogrid/core/multi_blade_row/single_blade_row.py
ansys/turbogrid/core/multi_blade_row/summary_template.html
ansys/turbogrid/core/ndf_parser/__init__.py
ansys/turbogrid/core/ndf_parser/ndf_parser.py
ansys_turbogrid_core-0.5.3.dist-info/METADATA
ansys_turbogrid_core-0.5.3.dist-info/WHEEL
ansys_turbogrid_core-0.5.3.dist-info/licenses/AUTHORS
ansys_turbogrid_core-0.5.3.dist-info/licenses/LICENSE
ansys_turbogrid_core-0.5.3.dist-info/RECORD
