Metadata-Version: 2.4
Name: ansys-turbogrid-core
Version: 0.5.3
Summary: A python wrapper for Ansys TurboGrid
License: MIT
License-File: AUTHORS
License-File: LICENSE
Author: ANSYS, Inc.
Author-email: pyansys.core@ansys.com
Maintainer: ANSYS, Inc.
Maintainer-email: pyansys.core@ansys.com
Requires-Python: >=3.10,<4.0
Classifier: Development Status :: 4 - Beta
Classifier: Intended Audience :: Science/Research
Classifier: License :: OSI Approved :: MIT License
Classifier: Operating System :: OS Independent
Classifier: Programming Language :: Python :: 3
Classifier: Programming Language :: Python :: 3.10
Classifier: Programming Language :: Python :: 3.11
Classifier: Programming Language :: Python :: 3.12
Classifier: Programming Language :: Python :: 3.13
Classifier: Programming Language :: Python :: 3.14
Classifier: Topic :: Scientific/Engineering :: Information Analysis
Requires-Dist: Jinja2 (>=3.1.2)
Requires-Dist: ansys-turbogrid-api (>=0.5.1)
Requires-Dist: deepdiff (>=8.4.2,<9.0.0)
Requires-Dist: fabric (>=3.2.2)
Requires-Dist: importlib-metadata (>=4.0)
Requires-Dist: matplotlib (>=3.5.1)
Requires-Dist: pyyaml (>=6.0.2,<7.0.0)
Project-URL: Documentation, https://turbogrid.docs.pyansys.com/version/stable/
Project-URL: Homepage, https://turbogrid.docs.pyansys.com
Project-URL: Repository, https://github.com/ansys/pyturbogrid
Project-URL: Source, https://github.com/ansys/pyturbogrid
Project-URL: Tracker, https://github.com/ansys/pyturbogrid/issues
